CSE3015-Digital-Logic-Design/Verilog/DLatch.v
module DLatch(D, Clock, Q);
    input D;
    input Clock;

    output Q;

    wire and1, and2, notD;
    not(notD, D);
    assign and1 = notD & Clock;
    assign and2 = D & Clock;

    wire nor1, nor2;

    nor(nor1, and1, nor2);
    nor(nor2, and2, nor1);

    assign Q = nor1;

endmodule

CSE3015-Digital-Logic-Design/Verilog/DFlipFlop.v
`include "DLatch.v"

module DFlipFlop(D, Clock, Enable, Q);
    input D;
    input Clock;
    input Enable;

    output Q;

    wire notClock, dlOutput1, dlOutput2;
    reg muxOutput;

    always @ (dlOutput2 or D or Enable) begin  
        case (Enable)  
            1'b0 : muxOutput <= dlOutput2;  
            1'b1 : muxOutput <= D;  
        endcase  
    end

    not(notClock, Clock);
    DLatch dl1 (muxOutput, notClock, dlOutput1);
    DLatch dl2 (dlOutput1, Clock, dlOutput2);

    assign Q = dlOutput2;

endmodule

CSE3015-Digital-Logic-Design/Verilog/DFlipFlop_tb.v
`include "DFlipFlop.v"

module DFlipFlop_tb;
    reg D;
    reg Clock;
    reg Enable;

    wire Q;

    DFlipFlop uut(D, Clock, Enable, Q);

    initial begin
        $dumpfile("DFlipFlop.vcd");
        $dumpvars(0, DFlipFlop_tb);

        D = 0;
        Clock = 0;
        Enable = 0;
        #20;

        D = 0;
        Clock = 0;
        Enable = 1;
        #20;

        D = 0;
        Clock = 1;
        Enable = 1;
        #20;

        D = 1;
        Clock = 1;
        Enable = 1;
        #20;

        D = 1;
        Clock = 0;
        Enable = 1;
        #20;

        D = 1;
        Clock = 1;
        Enable = 1;
        #20;

        D = 0;
        Clock = 1;
        Enable = 0;
        #20;

        D = 0;
        Clock = 1;
        Enable = 1;
        #20;

        D = 0;
        Clock = 1;
        Enable = 1;
        #20;

        D = 0;
        Clock = 0;
        Enable = 1;
        #20;

        D = 0;
        Clock = 1;
        Enable = 1;
        #20;

        $display("test completed");
    end
endmodule

CSE3015-Digital-Logic-Design/Verilog/DFlipFlop.vcd
$date
	Sun Jan 01 20:37:33 2023
$end
$version
	Icarus Verilog
$end
$timescale
	1s
$end
$scope module DFlipFlop_tb $end
$var wire 1 ! Q $end
$var reg 1 " Clock $end
$var reg 1 # D $end
$var reg 1 $ Enable $end
$scope module uut $end
$var wire 1 " Clock $end
$var wire 1 # D $end
$var wire 1 $ Enable $end
$var wire 1 ! Q $end
$var wire 1 % notClock $end
$var wire 1 & dlOutput2 $end
$var wire 1 ' dlOutput1 $end
$var reg 1 ( muxOutput $end
$scope module dl1 $end
$var wire 1 % Clock $end
$var wire 1 ( D $end
$var wire 1 ' Q $end
$var wire 1 ) and1 $end
$var wire 1 * and2 $end
$var wire 1 + nor1 $end
$var wire 1 , nor2 $end
$var wire 1 - notD $end
$upscope $end
$scope module dl2 $end
$var wire 1 " Clock $end
$var wire 1 ' D $end
$var wire 1 & Q $end
$var wire 1 . and1 $end
$var wire 1 / and2 $end
$var wire 1 0 nor1 $end
$var wire 1 1 nor2 $end
$var wire 1 2 notD $end
$upscope $end
$upscope $end
$upscope $end
$enddefinitions $end
$comment Show the parameter values. $end
$dumpall
$end
#0
$dumpvars
x2
x1
x0
0/
0.
x-
x,
x+
x*
x)
x(
x'
x&
1%
0$
0#
0"
x!
$end
#20
1,
12
0'
0+
1)
1-
0*
0(
1$
#40
11
0)
0!
0&
00
0%
1.
1"
#60
0-
1(
1#
#80
02
1'
1+
0,
1*
1%
0.
0"
#100
1!
1&
10
0*
01
0%
1/
1"
#120
0$
0#
#140
1-
0(
1$
#180
1,
12
0'
0+
1)
1%
0/
0"
#200
11
0)
0!
0&
00
0%
1.
1"
